README.md
setup.py
skeletonize/__init__.py
skeletonize/align.py
skeletonize/parser.py
skeletonize/renderer.py
skeletonize/reskeletonize.py
skeletonize/skeleton.py
skeletonize/tokenize.py
skeletonize.egg-info/PKG-INFO
skeletonize.egg-info/SOURCES.txt
skeletonize.egg-info/dependency_links.txt
skeletonize.egg-info/requires.txt
skeletonize.egg-info/top_level.txt