Metadata-Version: 2.1
Name: skeletonize
Version: 2.6
Summary: Handles skeletonization and deskeletonization of python code.
Home-page: https://github.com/kavigupta/skeletonize
Author: Kavi Gupta
Author-email: skeletonize@kavigupta.org
License: UNKNOWN
Platform: UNKNOWN
Classifier: Programming Language :: Python :: 3.5
Classifier: Programming Language :: Python :: 3.6
Classifier: Programming Language :: Python :: 3.7
Classifier: Programming Language :: Python :: 3.8
Classifier: Operating System :: OS Independent
Requires-Python: >=3.5
